{"url": "https://book.douban.com/subject/1000053/", "id": "1000053", "title": "室内步行街", "cover": "https://img1.doubanio.com/view/subject/l/public/s1000029.jpg", "base": "作者: 季振邦出版社:华东师范大学出版社出版年:1999-11页数:287定价:14.00装帧:平装ISBN:9787561721643", "intro": "本书共分四辑。前三辑的划分可能不够严密，不够科学。好在文学不是科学，不严密就不严密吧。第四辑包括两个部分：给别人写的序和作者自己的游记。这些文字都是观赏后的产物，因此这两部分统称为“观余赏后”。愿有非常多的读者喜欢这本书。季振邦，1947年生于崇明。读书、插队、上调。1969年开始发表作品。著有诗集《飞向明天》、《三叶草》，散文集《现代人调侃》、《谁能与我同侃》等。现为上海作家协会理事、诗歌委员会副主任，解放日报主任编辑、“朝花”副主编。", "tags": ["民谣", "中国摇滚"], "score": {"avg": "  ", "scroe_num": "", "rating": []}, "reviews": []}